README.rst
setup.py
./Models.py
./__init__.py
PyZekrModels.egg-info/PKG-INFO
PyZekrModels.egg-info/SOURCES.txt
PyZekrModels.egg-info/dependency_links.txt
PyZekrModels.egg-info/top_level.txt
PyZekrModels.egg-info/zip-safe